data_ml_utils/core/__init__.py
data_ml_utils/core/config.py
data_ml_utils/core/databricks_utils.py
data_ml_utils/core/pyathena_utils.py
data_ml_utils/mlflow_databricks/__init__.py
data_ml_utils/mlflow_databricks/mlflow_tracker.py
data_ml_utils/pyathena_client/__init__.py
data_ml_utils/pyathena_client/client.py
data_ml_utils-0.3.4.dist-info/LICENSE.txt
data_ml_utils-0.3.4.dist-info/WHEEL
data_ml_utils-0.3.4.dist-info/METADATA
data_ml_utils-0.3.4.dist-info/RECORD
